{"name":"其它","postlist":[{"title":"纪念史蒂夫·乔布斯逝世十周年","slug":"Steve-Jobs","date":"2021-10-05T14:24:36.000Z","updated":"2021-12-04T11:03:06.482Z","comments":true,"path":"api/articles/Steve-Jobs.json","excerpt":null,"keywords":"blog,Jerry_Zhou,JerryZhou,Jerry,YangguangZhou,周洋光,博客,个人博客,Hexo,butterfly,Github,编程,code,C++","cover":"https://img.examcoo.com/ask/7386438/202110/163344356028400.jpg","content":"<p>他改变了电脑。</p>\n<p>他改变了软件。</p>\n<p>他改变了设计。</p>\n<p>他改变了出版。</p>\n<p>他改变了电影。</p>\n<p>他改变了音乐。</p>\n<p>他改变了广告。</p>\n<p>他改变了零售。</p>\n<p>他改变了商业。</p>\n<p>他改变了米色。</p>\n<p>他改变了人们的期望。</p>\n<p>他改变了我们的思维。</p>\n<p>他改变了他们。</p>\n<p>他改变了我们。</p>\n<p>他改变了你。</p>\n<p><strong>他改变了整个世界。</strong></p>\n<p>别因终结而悲伤，因其诞生而微笑吧。</p>\n<p><strong>10 年了，我们还会去准备去改变什么？我们还会接受什么样的改变？</strong></p>\n<hr />\n<h1 id=\"纪念史蒂夫乔布斯逝世十周年\"><a class=\"markdownIt-Anchor\" href=\"#纪念史蒂夫乔布斯逝世十周年\"></a> <strong>纪念<a href=\"https://baike.baidu.com/item/%E5%8F%B2%E8%92%82%E5%A4%AB%C2%B7%E4%B9%94%E5%B8%83%E6%96%AF/85300?fromtitle=%E4%B9%94%E5%B8%83%E6%96%AF&amp;fromid=4694726&amp;fr=aladdin\">史蒂夫·乔布斯</a>逝世十周年</strong></h1>\n<p><strong>——一个改变了世界的人</strong></p>\n<p><img src=\"https://img.examcoo.com/ask/7386438/202110/163344356028400.jpg\" alt=\"史蒂夫·乔布斯\" /></p>\n","raw":null,"categories":[{"name":"其它","path":"api/categories/其它.json"}],"tags":[{"name":"苹果","path":"api/tags/苹果.json"},{"name":"科技","path":"api/tags/科技.json"}]},{"title":"关于我","slug":"about","date":"2021-11-27T14:15:23.000Z","updated":"2022-04-15T14:45:57.194Z","comments":true,"path":"api/articles/about.json","excerpt":null,"keywords":"blog,Jerry_Zhou,JerryZhou,Jerry,YangguangZhou,周洋光,博客,个人博客,Hexo,butterfly,Github,编程,code,C++","cover":"https://img.examcoo.com/ask/7386438/202112/163859146268730.png","content":"<p><img src=\"https://card.jerryz.com.cn/white\" alt=\"欢迎\"></p>\n<h1>个人简介</h1>\n<p>大家好，我是<code>Jerry Zhou</code>,今年初二，就读于<code>YN</code>的<code>YUSS</code>（<code>YN</code>最好的初中，但我在其中依然是一名蒟蒻）。我是一名<code>OIer</code>和数码爱好者<s>以及重度社恐患者（社交恐惧症+社交恐怖症）</s>。</p>\n<h2 id=\"我的个人主页\"><strong><a href=\"https://jerryz.com.cn\">我的个人主页</a></strong></h2>\n<h1>社交帐号</h1>\n<h2 id=\"我的社交账号\"><strong><a href=\"https://jerryz.com.cn/account\">我的社交账号</a></strong></h2>\n<h1>我的一些项目</h1>\n<h2 id=\"我的项目\"><strong><a href=\"https://jerryz.com.cn/program\">我的项目</a></strong></h2>\n<h1>我的目标</h1>\n<ul>\n<li>进入<code>YN</code>最好的高中<code>YNSDFZ</code></li>\n<li><a href=\"https://www.luogu.com.cn/\">洛谷</a>橙名</li>\n<li><a href=\"https://bytew.net/OIer/\">OIer排名</a>云南前二十</li>\n</ul>\n<h1>信息学所获奖项</h1>\n<ol>\n<li><code>CSP2020</code>入门一等奖：分数<code>100</code>，排名<code>7543</code></li>\n<li><code>CSP2021</code>入门一等奖：分数<code>101</code>，排名<code>7913</code></li>\n<li><code>CSP2021</code>提高：分数<code>15</code></li>\n<li><code>NOIP2021</code>：分数<code>62</code></li>\n</ol>\n<h1>支持一下</h1>\n<p><img src=\"https://img.examcoo.com/ask/7386438/202111/163807292857330.png\" alt=\"微信\"></p>\n<p><img src=\"https://img.examcoo.com/ask/7386438/202111/163807296626040.jpg\" alt=\"支付宝\"></p>\n","raw":null,"categories":[{"name":"其它","path":"api/categories/其它.json"}],"tags":[{"name":"个人","path":"api/tags/个人.json"}]}]}